<?xml version="1.0" standalone="yes"?>
<NewDataSet>
  <Insert_tbl_trans_menu>
    <mnu_id>6003</mnu_id>
    <mnu_menuName>Notification Topics</mnu_menuName>
    <mnu_menuLink>../management/IframeTopics.aspx</mnu_menuLink>
    <mun_parentId>151</mun_parentId>
    <mnu_segmentId>6</mnu_segmentId>
    <mnu_image>icohome.gif</mnu_image>
    <mnu_HaveSubMenu>N</mnu_HaveSubMenu>
  </Insert_tbl_trans_menu>
  <Insert_tbl_trans_menu>
    <mnu_id>6004</mnu_id>
    <mnu_menuName>Digital Signature Management</mnu_menuName>
    <mnu_menuLink>../management/UploadDigitalSignature.aspx</mnu_menuLink>
    <mun_parentId>171</mun_parentId>
    <mnu_segmentId>6</mnu_segmentId>
    <mnu_image>icohome.gif</mnu_image>
    <mnu_HaveSubMenu>N</mnu_HaveSubMenu>
  </Insert_tbl_trans_menu>
  <Insert_tbl_trans_menu>
    <mnu_id>7001</mnu_id>
    <mnu_menuName>Fund Manager</mnu_menuName>
    <mnu_menuLink>../management/FundManager.aspx</mnu_menuLink>
    <mun_parentId>570</mun_parentId>
    <mnu_segmentId>7</mnu_segmentId>
    <mnu_image>icohome.gif</mnu_image>
    <mnu_HaveSubMenu>N</mnu_HaveSubMenu>
  </Insert_tbl_trans_menu>
  <Insert_tbl_trans_menu>
    <mnu_id>8001</mnu_id>
    <mnu_menuName>Fund Manager</mnu_menuName>
    <mnu_menuLink>../management/FundManager.aspx</mnu_menuLink>
    <mun_parentId>781</mun_parentId>
    <mnu_segmentId>8</mnu_segmentId>
    <mnu_image>icohome.gif</mnu_image>
    <mnu_HaveSubMenu>N</mnu_HaveSubMenu>
  </Insert_tbl_trans_menu>
  <Insert_tbl_trans_menu>
    <mnu_id>11203</mnu_id>
    <mnu_menuName>Net Position/MTM</mnu_menuName>
    <mnu_menuLink>../Reports/NetPosition_MTM.aspx</mnu_menuLink>
    <mun_parentId>11087</mun_parentId>
    <mnu_segmentId>11</mnu_segmentId>
    <mnu_image>icohome.gif</mnu_image>
    <mnu_HaveSubMenu>N</mnu_HaveSubMenu>
  </Insert_tbl_trans_menu>
  <Insert_tbl_trans_menu>
    <mnu_id>13202</mnu_id>
    <mnu_menuName>Net Position/MTM</mnu_menuName>
    <mnu_menuLink>../Reports/NetPosition_MTM.aspx</mnu_menuLink>
    <mun_parentId>13093</mun_parentId>
    <mnu_segmentId>12</mnu_segmentId>
    <mnu_image>icohome.gif</mnu_image>
    <mnu_HaveSubMenu>N</mnu_HaveSubMenu>
  </Insert_tbl_trans_menu>
  <Update_tbl_trans_menu>
    <mnu_id>310</mnu_id>
    <mnu_menuName>Phone Calls</mnu_menuName>
    <mnu_menuLink>../management/CrmPhoneCallActivityWithIFrame.aspx</mnu_menuLink>
    <mun_parentId>309</mun_parentId>
    <mnu_segmentId>1</mnu_segmentId>
    <mnu_image>icohome.gif</mnu_image>
    <mnu_HaveSubMenu>N</mnu_HaveSubMenu>
  </Update_tbl_trans_menu>
  <Update_tbl_trans_menu>
    <mnu_id>573</mnu_id>
    <mnu_menuName>Custodians</mnu_menuName>
    <mnu_menuLink>../management/Custodian.aspx</mnu_menuLink>
    <mun_parentId>570</mun_parentId>
    <mnu_segmentId>7</mnu_segmentId>
    <mnu_image>icohome.gif</mnu_image>
    <mnu_HaveSubMenu>N</mnu_HaveSubMenu>
  </Update_tbl_trans_menu>
  <Update_tbl_trans_menu>
    <mnu_id>614</mnu_id>
    <mnu_menuName>Trade Processing</mnu_menuName>
    <mnu_menuLink>../management/Trade_Processingiframe.aspx</mnu_menuLink>
    <mun_parentId>587</mun_parentId>
    <mnu_segmentId>7</mnu_segmentId>
    <mnu_image>icohome.gif</mnu_image>
    <mnu_HaveSubMenu>N</mnu_HaveSubMenu>
  </Update_tbl_trans_menu>
  <Update_tbl_trans_menu>
    <mnu_id>615</mnu_id>
    <mnu_menuName>Contract Number Generation</mnu_menuName>
    <mnu_menuLink>../management/contractnogenarationiframe.aspx</mnu_menuLink>
    <mun_parentId>587</mun_parentId>
    <mnu_segmentId>7</mnu_segmentId>
    <mnu_image>icohome.gif</mnu_image>
    <mnu_HaveSubMenu>N</mnu_HaveSubMenu>
  </Update_tbl_trans_menu>
  <Update_tbl_trans_menu>
    <mnu_id>653</mnu_id>
    <mnu_menuName>Trade Registers</mnu_menuName>
    <mnu_menuLink>../Reports/frmReport_TradeRegisteriframe.aspx</mnu_menuLink>
    <mun_parentId>652</mun_parentId>
    <mnu_segmentId>7</mnu_segmentId>
    <mnu_image>icohome.gif</mnu_image>
    <mnu_HaveSubMenu>N</mnu_HaveSubMenu>
  </Update_tbl_trans_menu>
  <Update_tbl_trans_menu>
    <mnu_id>662</mnu_id>
    <mnu_menuName>Contract Register</mnu_menuName>
    <mnu_menuLink>../Reports/contractregisteriframe.aspx</mnu_menuLink>
    <mun_parentId>652</mun_parentId>
    <mnu_segmentId>7</mnu_segmentId>
    <mnu_image>icohome.gif</mnu_image>
    <mnu_HaveSubMenu>N</mnu_HaveSubMenu>
  </Update_tbl_trans_menu>
  <Update_tbl_trans_menu>
    <mnu_id>666</mnu_id>
    <mnu_menuName>Brokerage Statement</mnu_menuName>
    <mnu_menuLink>../Reports/frmReport_BrokerageChargesiframe.aspx</mnu_menuLink>
    <mun_parentId>664</mun_parentId>
    <mnu_segmentId>7</mnu_segmentId>
    <mnu_image>icohome.gif</mnu_image>
    <mnu_HaveSubMenu>N</mnu_HaveSubMenu>
  </Update_tbl_trans_menu>
  <Update_tbl_trans_menu>
    <mnu_id>784</mnu_id>
    <mnu_menuName>Custodians</mnu_menuName>
    <mnu_menuLink>../management/Custodian.aspx</mnu_menuLink>
    <mun_parentId>781</mun_parentId>
    <mnu_segmentId>8</mnu_segmentId>
    <mnu_image>icohome.gif</mnu_image>
    <mnu_HaveSubMenu>N</mnu_HaveSubMenu>
  </Update_tbl_trans_menu>
  <Update_tbl_trans_menu>
    <mnu_id>801</mnu_id>
    <mnu_menuName>Trades</mnu_menuName>
    <mnu_menuLink>../management/fotradesiframe.aspx</mnu_menuLink>
    <mun_parentId>799</mun_parentId>
    <mnu_segmentId>8</mnu_segmentId>
    <mnu_image>icohome.gif</mnu_image>
    <mnu_HaveSubMenu>N</mnu_HaveSubMenu>
  </Update_tbl_trans_menu>
  <Update_tbl_trans_menu>
    <mnu_id>802</mnu_id>
    <mnu_menuName>Closing Rates</mnu_menuName>
    <mnu_menuLink>../management/FoClosingrateiframe.aspx</mnu_menuLink>
    <mun_parentId>799</mun_parentId>
    <mnu_segmentId>8</mnu_segmentId>
    <mnu_image>icohome.gif</mnu_image>
    <mnu_HaveSubMenu>N</mnu_HaveSubMenu>
  </Update_tbl_trans_menu>
  <Update_tbl_trans_menu>
    <mnu_id>804</mnu_id>
    <mnu_menuName>Margins</mnu_menuName>
    <mnu_menuLink>../management/Marginfoiframe.aspx</mnu_menuLink>
    <mun_parentId>799</mun_parentId>
    <mnu_segmentId>8</mnu_segmentId>
    <mnu_image>icohome.gif</mnu_image>
    <mnu_HaveSubMenu>N</mnu_HaveSubMenu>
  </Update_tbl_trans_menu>
  <Update_tbl_trans_menu>
    <mnu_id>805</mnu_id>
    <mnu_menuName>STT Files</mnu_menuName>
    <mnu_menuLink>../management/sttfoiframe.aspx</mnu_menuLink>
    <mun_parentId>799</mun_parentId>
    <mnu_segmentId>8</mnu_segmentId>
    <mnu_image>icohome.gif</mnu_image>
    <mnu_HaveSubMenu>N</mnu_HaveSubMenu>
  </Update_tbl_trans_menu>
  <Update_tbl_trans_menu>
    <mnu_id>823</mnu_id>
    <mnu_menuName>Trade Processing</mnu_menuName>
    <mnu_menuLink>../management/Trade_Processingiframe.aspx</mnu_menuLink>
    <mun_parentId>798</mun_parentId>
    <mnu_segmentId>8</mnu_segmentId>
    <mnu_image>icohome.gif</mnu_image>
    <mnu_HaveSubMenu>N</mnu_HaveSubMenu>
  </Update_tbl_trans_menu>
  <Update_tbl_trans_menu>
    <mnu_id>824</mnu_id>
    <mnu_menuName>Contract Number Generation</mnu_menuName>
    <mnu_menuLink>../management/contractnogenarationiframe.aspx</mnu_menuLink>
    <mun_parentId>798</mun_parentId>
    <mnu_segmentId>8</mnu_segmentId>
    <mnu_image>icohome.gif</mnu_image>
    <mnu_HaveSubMenu>N</mnu_HaveSubMenu>
  </Update_tbl_trans_menu>
  <Update_tbl_trans_menu>
    <mnu_id>858</mnu_id>
    <mnu_menuName>Trade Registers</mnu_menuName>
    <mnu_menuLink>../Reports/frmReport_TradeRegisteriframe.aspx</mnu_menuLink>
    <mun_parentId>857</mun_parentId>
    <mnu_segmentId>8</mnu_segmentId>
    <mnu_image>icohome.gif</mnu_image>
    <mnu_HaveSubMenu>N</mnu_HaveSubMenu>
  </Update_tbl_trans_menu>
  <Update_tbl_trans_menu>
    <mnu_id>867</mnu_id>
    <mnu_menuName>STT Register</mnu_menuName>
    <mnu_menuLink>../management/frm_sttregister_iframeFo.aspx</mnu_menuLink>
    <mun_parentId>857</mun_parentId>
    <mnu_segmentId>8</mnu_segmentId>
    <mnu_image>icohome.gif</mnu_image>
    <mnu_HaveSubMenu>N</mnu_HaveSubMenu>
  </Update_tbl_trans_menu>
  <Update_tbl_trans_menu>
    <mnu_id>868</mnu_id>
    <mnu_menuName>Contract Register</mnu_menuName>
    <mnu_menuLink>../Reports/contractregisteriframe.aspx</mnu_menuLink>
    <mun_parentId>857</mun_parentId>
    <mnu_segmentId>8</mnu_segmentId>
    <mnu_image>icohome.gif</mnu_image>
    <mnu_HaveSubMenu>N</mnu_HaveSubMenu>
  </Update_tbl_trans_menu>
  <Update_tbl_trans_menu>
    <mnu_id>872</mnu_id>
    <mnu_menuName>Brokerage Statement</mnu_menuName>
    <mnu_menuLink>../Reports/frmReport_BrokerageChargesiframe.aspx</mnu_menuLink>
    <mun_parentId>870</mun_parentId>
    <mnu_segmentId>8</mnu_segmentId>
    <mnu_image>icohome.gif</mnu_image>
    <mnu_HaveSubMenu>N</mnu_HaveSubMenu>
  </Update_tbl_trans_menu>
  <Update_tbl_trans_menu>
    <mnu_id>922</mnu_id>
    <mnu_menuName>Cash/Bank Book</mnu_menuName>
    <mnu_menuLink>../reports/frmReport_IFrameCashBankBook.aspx</mnu_menuLink>
    <mun_parentId>921</mun_parentId>
    <mnu_segmentId>8</mnu_segmentId>
    <mnu_image>icohome.gif</mnu_image>
    <mnu_HaveSubMenu>N</mnu_HaveSubMenu>
  </Update_tbl_trans_menu>
  <Update_tbl_trans_menu>
    <mnu_id>927</mnu_id>
    <mnu_menuName>General Trial</mnu_menuName>
    <mnu_menuLink>../reports/frmReport_IframeGeneralTrial.aspx</mnu_menuLink>
    <mun_parentId>926</mun_parentId>
    <mnu_segmentId>8</mnu_segmentId>
    <mnu_image>icohome.gif</mnu_image>
    <mnu_HaveSubMenu>N</mnu_HaveSubMenu>
  </Update_tbl_trans_menu>
  <Update_tbl_trans_menu>
    <mnu_id>928</mnu_id>
    <mnu_menuName>Subsidiary Trial</mnu_menuName>
    <mnu_menuLink>../reports/frmReport_IframeSubsidiaryTrial.aspx</mnu_menuLink>
    <mun_parentId>926</mun_parentId>
    <mnu_segmentId>8</mnu_segmentId>
    <mnu_image>icohome.gif</mnu_image>
    <mnu_HaveSubMenu>N</mnu_HaveSubMenu>
  </Update_tbl_trans_menu>
  <Update_tbl_trans_menu>
    <mnu_id>931</mnu_id>
    <mnu_menuName>Ledgers</mnu_menuName>
    <mnu_menuLink>../reports/frmReport_IFrameLedgerView.aspx</mnu_menuLink>
    <mun_parentId>921</mun_parentId>
    <mnu_segmentId>8</mnu_segmentId>
    <mnu_image>icohome.gif</mnu_image>
    <mnu_HaveSubMenu>N</mnu_HaveSubMenu>
  </Update_tbl_trans_menu>
  <Update_tbl_trans_menu>
    <mnu_id>1222</mnu_id>
    <mnu_menuName>Bill Printing</mnu_menuName>
    <mnu_menuLink>../Reports/cdslBill_Print_Iframe.aspx?type=NSDL</mnu_menuLink>
    <mun_parentId>1189</mun_parentId>
    <mnu_segmentId>9</mnu_segmentId>
    <mnu_image>icohome.gif</mnu_image>
    <mnu_HaveSubMenu>N</mnu_HaveSubMenu>
  </Update_tbl_trans_menu>
  <Update_tbl_trans_menu>
    <mnu_id>1273</mnu_id>
    <mnu_menuName>Cash/Bank Book</mnu_menuName>
    <mnu_menuLink>../Reports/frmReport_IframeGeneralTrial.aspx</mnu_menuLink>
    <mun_parentId>1272</mun_parentId>
    <mnu_segmentId>9</mnu_segmentId>
    <mnu_image>icohome.gif</mnu_image>
    <mnu_HaveSubMenu>N</mnu_HaveSubMenu>
  </Update_tbl_trans_menu>
  <Update_tbl_trans_menu>
    <mnu_id>1277</mnu_id>
    <mnu_menuName>General Trial</mnu_menuName>
    <mnu_menuLink>../Reports/frmReport_IframeGeneralTrial.aspx</mnu_menuLink>
    <mun_parentId>1276</mun_parentId>
    <mnu_segmentId>9</mnu_segmentId>
    <mnu_image>icohome.gif</mnu_image>
    <mnu_HaveSubMenu>N</mnu_HaveSubMenu>
  </Update_tbl_trans_menu>
  <Update_tbl_trans_menu>
    <mnu_id>1278</mnu_id>
    <mnu_menuName>Subsidiary Trial</mnu_menuName>
    <mnu_menuLink>../Reports/frmReport_IframeSubsidiaryTrial.aspx</mnu_menuLink>
    <mun_parentId>1276</mun_parentId>
    <mnu_segmentId>9</mnu_segmentId>
    <mnu_image>icohome.gif</mnu_image>
    <mnu_HaveSubMenu>N</mnu_HaveSubMenu>
  </Update_tbl_trans_menu>
  <Update_tbl_trans_menu>
    <mnu_id>1281</mnu_id>
    <mnu_menuName>Ledgers</mnu_menuName>
    <mnu_menuLink>../Reports/frmReport_IframeGeneralTrial.aspx</mnu_menuLink>
    <mun_parentId>1272</mun_parentId>
    <mnu_segmentId>9</mnu_segmentId>
    <mnu_image>icohome.gif</mnu_image>
    <mnu_HaveSubMenu>N</mnu_HaveSubMenu>
  </Update_tbl_trans_menu>
  <Update_tbl_trans_menu>
    <mnu_id>1366</mnu_id>
    <mnu_menuName>Statement Of Transaction</mnu_menuName>
    <mnu_menuLink>../management/cdslTransctioniframe.aspx</mnu_menuLink>
    <mun_parentId>1357</mun_parentId>
    <mnu_segmentId>10</mnu_segmentId>
    <mnu_image>icohome.gif</mnu_image>
    <mnu_HaveSubMenu>N</mnu_HaveSubMenu>
  </Update_tbl_trans_menu>
  <Update_tbl_trans_menu>
    <mnu_id>1386</mnu_id>
    <mnu_menuName>Bill Printing</mnu_menuName>
    <mnu_menuLink>../Reports/cdslBill_Print_Iframe.aspx?type=CDSL</mnu_menuLink>
    <mun_parentId>1356</mun_parentId>
    <mnu_segmentId>10</mnu_segmentId>
    <mnu_image>icohome.gif</mnu_image>
    <mnu_HaveSubMenu>N</mnu_HaveSubMenu>
  </Update_tbl_trans_menu>
  <Update_tbl_trans_menu>
    <mnu_id>1408</mnu_id>
    <mnu_menuName>Bill Register</mnu_menuName>
    <mnu_menuLink>../reports/frmReport_cdslBill.aspx?type=CDSL</mnu_menuLink>
    <mun_parentId>1406</mun_parentId>
    <mnu_segmentId>10</mnu_segmentId>
    <mnu_image>icohome.gif</mnu_image>
    <mnu_HaveSubMenu>N</mnu_HaveSubMenu>
  </Update_tbl_trans_menu>
  <Update_tbl_trans_menu>
    <mnu_id>1437</mnu_id>
    <mnu_menuName>Cash/Bank Book</mnu_menuName>
    <mnu_menuLink>../Reports/frmReport_IFrameCashBankBook.aspx</mnu_menuLink>
    <mun_parentId>1436</mun_parentId>
    <mnu_segmentId>10</mnu_segmentId>
    <mnu_image>icohome.gif</mnu_image>
    <mnu_HaveSubMenu>N</mnu_HaveSubMenu>
  </Update_tbl_trans_menu>
  <Update_tbl_trans_menu>
    <mnu_id>1441</mnu_id>
    <mnu_menuName>General Trial</mnu_menuName>
    <mnu_menuLink>../reports/frmReport_IframeGeneralTrial.aspx</mnu_menuLink>
    <mun_parentId>1440</mun_parentId>
    <mnu_segmentId>10</mnu_segmentId>
    <mnu_image>icohome.gif</mnu_image>
    <mnu_HaveSubMenu>N</mnu_HaveSubMenu>
  </Update_tbl_trans_menu>
  <Update_tbl_trans_menu>
    <mnu_id>1442</mnu_id>
    <mnu_menuName>Subsidiary Trial</mnu_menuName>
    <mnu_menuLink>../reports/frmReport_IframeSubsidiaryTrial.aspx</mnu_menuLink>
    <mun_parentId>1440</mun_parentId>
    <mnu_segmentId>10</mnu_segmentId>
    <mnu_image>icohome.gif</mnu_image>
    <mnu_HaveSubMenu>N</mnu_HaveSubMenu>
  </Update_tbl_trans_menu>
  <Update_tbl_trans_menu>
    <mnu_id>1445</mnu_id>
    <mnu_menuName>Ledgers</mnu_menuName>
    <mnu_menuLink>../Reports/frmReport_IFrameLedgerView.aspx</mnu_menuLink>
    <mun_parentId>1436</mun_parentId>
    <mnu_segmentId>10</mnu_segmentId>
    <mnu_image>icohome.gif</mnu_image>
    <mnu_HaveSubMenu>N</mnu_HaveSubMenu>
  </Update_tbl_trans_menu>
  <Update_tbl_trans_menu>
    <mnu_id>3003</mnu_id>
    <mnu_menuName>Insurance Commission Slabs</mnu_menuName>
    <mnu_menuLink>../Management/frmwip.aspx</mnu_menuLink>
    <mun_parentId>452</mun_parentId>
    <mnu_segmentId>3</mnu_segmentId>
    <mnu_image>icohome.gif</mnu_image>
    <mnu_HaveSubMenu>N</mnu_HaveSubMenu>
  </Update_tbl_trans_menu>
  <Update_tbl_trans_menu>
    <mnu_id>11009</mnu_id>
    <mnu_menuName>Derivatives</mnu_menuName>
    <mnu_menuLink>../management/frmProductComDerivatives_iframe.aspx</mnu_menuLink>
    <mun_parentId>11008</mun_parentId>
    <mnu_segmentId>11</mnu_segmentId>
    <mnu_image>icohome.gif</mnu_image>
    <mnu_HaveSubMenu>N</mnu_HaveSubMenu>
  </Update_tbl_trans_menu>
  <Update_tbl_trans_menu>
    <mnu_id>11010</mnu_id>
    <mnu_menuName>Commodities</mnu_menuName>
    <mnu_menuLink>../management/frmProductCommodity_iframe.aspx</mnu_menuLink>
    <mun_parentId>11008</mun_parentId>
    <mnu_segmentId>11</mnu_segmentId>
    <mnu_image>icohome.gif</mnu_image>
    <mnu_HaveSubMenu>N</mnu_HaveSubMenu>
  </Update_tbl_trans_menu>
  <Update_tbl_trans_menu>
    <mnu_id>11033</mnu_id>
    <mnu_menuName>Contracts</mnu_menuName>
    <mnu_menuLink>../management/ICEXContracts_iframe.aspx</mnu_menuLink>
    <mun_parentId>11032</mun_parentId>
    <mnu_segmentId>11</mnu_segmentId>
    <mnu_image>icohome.gif</mnu_image>
    <mnu_HaveSubMenu>N</mnu_HaveSubMenu>
  </Update_tbl_trans_menu>
  <Update_tbl_trans_menu>
    <mnu_id>11034</mnu_id>
    <mnu_menuName>Trades</mnu_menuName>
    <mnu_menuLink>../management/icextrades_iframe.aspx</mnu_menuLink>
    <mun_parentId>11032</mun_parentId>
    <mnu_segmentId>11</mnu_segmentId>
    <mnu_image>icohome.gif</mnu_image>
    <mnu_HaveSubMenu>N</mnu_HaveSubMenu>
  </Update_tbl_trans_menu>
  <Update_tbl_trans_menu>
    <mnu_id>11035</mnu_id>
    <mnu_menuName>Closing Rates</mnu_menuName>
    <mnu_menuLink>../management/icexclosingRats_iframe.aspx</mnu_menuLink>
    <mun_parentId>11032</mun_parentId>
    <mnu_segmentId>11</mnu_segmentId>
    <mnu_image>icohome.gif</mnu_image>
    <mnu_HaveSubMenu>N</mnu_HaveSubMenu>
  </Update_tbl_trans_menu>
  <Update_tbl_trans_menu>
    <mnu_id>11055</mnu_id>
    <mnu_menuName>Trade Processing</mnu_menuName>
    <mnu_menuLink>../management/TradeProcessing.aspx</mnu_menuLink>
    <mun_parentId>11031</mun_parentId>
    <mnu_segmentId>11</mnu_segmentId>
    <mnu_image>icohome.gif</mnu_image>
    <mnu_HaveSubMenu>N</mnu_HaveSubMenu>
  </Update_tbl_trans_menu>
  <Update_tbl_trans_menu>
    <mnu_id>11056</mnu_id>
    <mnu_menuName>Contract Number Generation</mnu_menuName>
    <mnu_menuLink>../management/contractnogenarationiframe.aspx</mnu_menuLink>
    <mun_parentId>11031</mun_parentId>
    <mnu_segmentId>11</mnu_segmentId>
    <mnu_image>icohome.gif</mnu_image>
    <mnu_HaveSubMenu>N</mnu_HaveSubMenu>
  </Update_tbl_trans_menu>
  <Update_tbl_trans_menu>
    <mnu_id>11088</mnu_id>
    <mnu_menuName>Trade Registers</mnu_menuName>
    <mnu_menuLink>../Reports/frmReportTradeRegisteriframe.aspx</mnu_menuLink>
    <mun_parentId>11087</mun_parentId>
    <mnu_segmentId>11</mnu_segmentId>
    <mnu_image>icohome.gif</mnu_image>
    <mnu_HaveSubMenu>N</mnu_HaveSubMenu>
  </Update_tbl_trans_menu>
  <Update_tbl_trans_menu>
    <mnu_id>11089</mnu_id>
    <mnu_menuName>Exchange Obligation</mnu_menuName>
    <mnu_menuLink>../Reports/frmReportExchangeObligation.aspx</mnu_menuLink>
    <mun_parentId>11087</mun_parentId>
    <mnu_segmentId>11</mnu_segmentId>
    <mnu_image>icohome.gif</mnu_image>
    <mnu_HaveSubMenu>N</mnu_HaveSubMenu>
  </Update_tbl_trans_menu>
  <Update_tbl_trans_menu>
    <mnu_id>11101</mnu_id>
    <mnu_menuName>Brokerage Statement</mnu_menuName>
    <mnu_menuLink>../Reports/frmReport_BrokerageStatement.aspx</mnu_menuLink>
    <mun_parentId>11099</mun_parentId>
    <mnu_segmentId>11</mnu_segmentId>
    <mnu_image>icohome.gif</mnu_image>
    <mnu_HaveSubMenu>N</mnu_HaveSubMenu>
  </Update_tbl_trans_menu>
  <Update_tbl_trans_menu>
    <mnu_id>11149</mnu_id>
    <mnu_menuName>Cash/Bank Book</mnu_menuName>
    <mnu_menuLink>../Reports/frmReport_IFrameCashBankBook.aspx</mnu_menuLink>
    <mun_parentId>11148</mun_parentId>
    <mnu_segmentId>11</mnu_segmentId>
    <mnu_image>icohome.gif</mnu_image>
    <mnu_HaveSubMenu>N</mnu_HaveSubMenu>
  </Update_tbl_trans_menu>
  <Update_tbl_trans_menu>
    <mnu_id>13009</mnu_id>
    <mnu_menuName>Derivatives</mnu_menuName>
    <mnu_menuLink>../management/frmProductComDerivatives_iframe.aspx</mnu_menuLink>
    <mun_parentId>13008</mun_parentId>
    <mnu_segmentId>12</mnu_segmentId>
    <mnu_image>icohome.gif</mnu_image>
    <mnu_HaveSubMenu>N</mnu_HaveSubMenu>
  </Update_tbl_trans_menu>
  <Update_tbl_trans_menu>
    <mnu_id>13010</mnu_id>
    <mnu_menuName>Commodities</mnu_menuName>
    <mnu_menuLink>../management/frmProductCommodity_iframe.aspx</mnu_menuLink>
    <mun_parentId>13008</mun_parentId>
    <mnu_segmentId>12</mnu_segmentId>
    <mnu_image>icohome.gif</mnu_image>
    <mnu_HaveSubMenu>N</mnu_HaveSubMenu>
  </Update_tbl_trans_menu>
  <Update_tbl_trans_menu>
    <mnu_id>13038</mnu_id>
    <mnu_menuName>Contracts</mnu_menuName>
    <mnu_menuLink>../management/frm_MCEXContracts.aspx</mnu_menuLink>
    <mun_parentId>13037</mun_parentId>
    <mnu_segmentId>12</mnu_segmentId>
    <mnu_image>icohome.gif</mnu_image>
    <mnu_HaveSubMenu>N</mnu_HaveSubMenu>
  </Update_tbl_trans_menu>
  <Update_tbl_trans_menu>
    <mnu_id>13039</mnu_id>
    <mnu_menuName>Trades</mnu_menuName>
    <mnu_menuLink>../management/frm_MCXTRADES.aspx</mnu_menuLink>
    <mun_parentId>13037</mun_parentId>
    <mnu_segmentId>12</mnu_segmentId>
    <mnu_image>icohome.gif</mnu_image>
    <mnu_HaveSubMenu>N</mnu_HaveSubMenu>
  </Update_tbl_trans_menu>
  <Update_tbl_trans_menu>
    <mnu_id>13040</mnu_id>
    <mnu_menuName>Closing Rates</mnu_menuName>
    <mnu_menuLink>../management/frm_MCXClosingRates.aspx</mnu_menuLink>
    <mun_parentId>13037</mun_parentId>
    <mnu_segmentId>12</mnu_segmentId>
    <mnu_image>icohome.gif</mnu_image>
    <mnu_HaveSubMenu>N</mnu_HaveSubMenu>
  </Update_tbl_trans_menu>
  <Update_tbl_trans_menu>
    <mnu_id>13060</mnu_id>
    <mnu_menuName>Trade Processing</mnu_menuName>
    <mnu_menuLink>../management/TradeProcessing.aspx</mnu_menuLink>
    <mun_parentId>13036</mun_parentId>
    <mnu_segmentId>12</mnu_segmentId>
    <mnu_image>icohome.gif</mnu_image>
    <mnu_HaveSubMenu>N</mnu_HaveSubMenu>
  </Update_tbl_trans_menu>
  <Update_tbl_trans_menu>
    <mnu_id>13094</mnu_id>
    <mnu_menuName>Trade Registers</mnu_menuName>
    <mnu_menuLink>../Reports/frmReportTradeRegisteriframe.aspx</mnu_menuLink>
    <mun_parentId>13093</mun_parentId>
    <mnu_segmentId>12</mnu_segmentId>
    <mnu_image>icohome.gif</mnu_image>
    <mnu_HaveSubMenu>N</mnu_HaveSubMenu>
  </Update_tbl_trans_menu>
  <Update_tbl_trans_menu>
    <mnu_id>13095</mnu_id>
    <mnu_menuName>Exchange Obligation</mnu_menuName>
    <mnu_menuLink>../Reports/frmReportExchangeObligation.aspx</mnu_menuLink>
    <mun_parentId>13093</mun_parentId>
    <mnu_segmentId>12</mnu_segmentId>
    <mnu_image>icohome.gif</mnu_image>
    <mnu_HaveSubMenu>N</mnu_HaveSubMenu>
  </Update_tbl_trans_menu>
  <Update_tbl_trans_menu>
    <mnu_id>13107</mnu_id>
    <mnu_menuName>Brokerage Statement</mnu_menuName>
    <mnu_menuLink>../Reports/frmReport_BrokerageStatement.aspx</mnu_menuLink>
    <mun_parentId>13105</mun_parentId>
    <mnu_segmentId>12</mnu_segmentId>
    <mnu_image>icohome.gif</mnu_image>
    <mnu_HaveSubMenu>N</mnu_HaveSubMenu>
  </Update_tbl_trans_menu>
  <Update_tbl_trans_menu>
    <mnu_id>13155</mnu_id>
    <mnu_menuName>Cash/Bank Book</mnu_menuName>
    <mnu_menuLink>../Reports/frmReport_IFrameCashBankBook.aspx</mnu_menuLink>
    <mun_parentId>13154</mun_parentId>
    <mnu_segmentId>12</mnu_segmentId>
    <mnu_image>icohome.gif</mnu_image>
    <mnu_HaveSubMenu>N</mnu_HaveSubMenu>
  </Update_tbl_trans_menu>
  <Insert_Master_UOM>
    <UOM_ID>1</UOM_ID>
    <UOM_Name>Number</UOM_Name>
    <UOM_UsedFor>Count</UOM_UsedFor>
    <UOM_ShortName>NUM</UOM_ShortName>
  </Insert_Master_UOM>
  <Insert_Master_UOM>
    <UOM_ID>2</UOM_ID>
    <UOM_Name>Kilogram</UOM_Name>
    <UOM_UsedFor>Weight</UOM_UsedFor>
    <UOM_ShortName>KG</UOM_ShortName>
  </Insert_Master_UOM>
  <Insert_Master_UOM>
    <UOM_ID>3</UOM_ID>
    <UOM_Name>Metric Ton</UOM_Name>
    <UOM_UsedFor>Weight</UOM_UsedFor>
    <UOM_ShortName>MT</UOM_ShortName>
  </Insert_Master_UOM>
  <Insert_Master_UOM>
    <UOM_ID>4</UOM_ID>
    <UOM_Name>Million Metric British Thermal Unit</UOM_Name>
    <UOM_UsedFor>Volume</UOM_UsedFor>
    <UOM_ShortName>mmBtu</UOM_ShortName>
  </Insert_Master_UOM>
  <Insert_Master_UOM>
    <UOM_ID>5</UOM_ID>
    <UOM_Name>Barrels</UOM_Name>
    <UOM_UsedFor>Volume</UOM_UsedFor>
    <UOM_ShortName>BARREL</UOM_ShortName>
  </Insert_Master_UOM>
  <Insert_Master_UOM>
    <UOM_ID>6</UOM_ID>
    <UOM_Name>Grams</UOM_Name>
    <UOM_UsedFor>Weight</UOM_UsedFor>
    <UOM_ShortName>GMS</UOM_ShortName>
  </Insert_Master_UOM>
  <Insert_Master_UOM>
    <UOM_ID>7</UOM_ID>
    <UOM_Name>Quintal</UOM_Name>
    <UOM_UsedFor>Weight</UOM_UsedFor>
    <UOM_ShortName>Quintal</UOM_ShortName>
  </Insert_Master_UOM>
  <Insert_Master_UOM>
    <UOM_ID>8</UOM_ID>
    <UOM_Name>Cotton Bales</UOM_Name>
    <UOM_UsedFor>Volume</UOM_UsedFor>
    <UOM_ShortName>BALES</UOM_ShortName>
  </Insert_Master_UOM>
  <Insert_Master_UOM>
    <UOM_ID>9</UOM_ID>
    <UOM_Name>Candy</UOM_Name>
    <UOM_UsedFor>Volume</UOM_UsedFor>
    <UOM_ShortName>CANDY</UOM_ShortName>
  </Insert_Master_UOM>
  <Insert_Master_UOM>
    <UOM_ID>10</UOM_ID>
    <UOM_Name>Maund</UOM_Name>
    <UOM_UsedFor>Weight</UOM_UsedFor>
    <UOM_ShortName>MAUND</UOM_ShortName>
  </Insert_Master_UOM>
  <Insert_Master_UOM>
    <UOM_ID>11</UOM_ID>
    <UOM_Name>Mega Watt Hour</UOM_Name>
    <UOM_UsedFor>Electricity</UOM_UsedFor>
    <UOM_ShortName>MWH</UOM_ShortName>
  </Insert_Master_UOM>
  <Insert_Master_UOM>
    <UOM_ID>12</UOM_ID>
    <UOM_Name>US Dollar</UOM_Name>
    <UOM_UsedFor>Currency</UOM_UsedFor>
    <UOM_ShortName>USD</UOM_ShortName>
  </Insert_Master_UOM>
  <Insert_Master_UOM>
    <UOM_ID>13</UOM_ID>
    <UOM_Name>US Gallon</UOM_Name>
    <UOM_UsedFor>Volume</UOM_UsedFor>
    <UOM_ShortName>USGLN</UOM_ShortName>
  </Insert_Master_UOM>
</NewDataSet>